{
  "id": "ff4597dd-64bb-4fa2-a7b9-383a290785bf",
  "prevId": "00000000-0000-0000-0000-000000000000",
  "version": "7",
  "dialect": "postgresql",
  "tables": {
    "public.highlight_table": {
      "name": "highlight_table",
      "schema": "",
      "columns": {
        "id": {
          "name": "id",
          "type": "serial",
          "primaryKey": true,
          "notNull": true
        },
        "user_id": {
          "name": "user_id",
          "type": "integer",
          "primaryKey": false,
          "notNull": true
        },
        "target_url": {
          "name": "target_url",
          "type": "varchar",
          "primaryKey": false,
          "notNull": true
        },
        "selector": {
          "name": "selector",
          "type": "varchar",
          "primaryKey": false,
          "notNull": true
        },
        "spans": {
          "name": "spans",
          "type": "json[]",
          "primaryKey": false,
          "notNull": true
        },
        "created_at": {
          "name": "created_at",
          "type": "timestamp",
          "primaryKey": false,
          "notNull": true,
          "default": "now()"
        },
        "updated_at": {
          "name": "updated_at",
          "type": "timestamp",
          "primaryKey": false,
          "notNull": true,
          "default": "now()"
        },
        "deleted_at": {
          "name": "deleted_at",
          "type": "timestamp",
          "primaryKey": false,
          "notNull": false
        }
      },
      "indexes": {
        "user_id_target_url_selector_highlights_idx": {
          "name": "user_id_target_url_selector_highlights_idx",
          "columns": [
            {
              "expression": "user_id",
              "isExpression": false,
              "asc": true,
              "nulls": "last"
            },
            {
              "expression": "target_url",
              "isExpression": false,
              "asc": true,
              "nulls": "last"
            },
            {
              "expression": "selector",
              "isExpression": false,
              "asc": true,
              "nulls": "last"
            }
          ],
          "isUnique": true,
          "where": "\"highlight_table\".\"deleted_at\" is null",
          "concurrently": false,
          "method": "btree",
          "with": {}
        }
      },
      "foreignKeys": {
        "highlight_table_user_id_user_table_id_fk": {
          "name": "highlight_table_user_id_user_table_id_fk",
          "tableFrom": "highlight_table",
          "tableTo": "user_table",
          "columnsFrom": [
            "user_id"
          ],
          "columnsTo": [
            "id"
          ],
          "onDelete": "no action",
          "onUpdate": "no action"
        }
      },
      "compositePrimaryKeys": {},
      "uniqueConstraints": {},
      "policies": {},
      "checkConstraints": {},
      "isRLSEnabled": false
    },
    "public.node_table": {
      "name": "node_table",
      "schema": "",
      "columns": {
        "id": {
          "name": "id",
          "type": "serial",
          "primaryKey": true,
          "notNull": true
        },
        "local_id": {
          "name": "local_id",
          "type": "varchar",
          "primaryKey": false,
          "notNull": true
        },
        "user_id": {
          "name": "user_id",
          "type": "integer",
          "primaryKey": false,
          "notNull": true
        },
        "target_url": {
          "name": "target_url",
          "type": "varchar",
          "primaryKey": false,
          "notNull": true
        },
        "domain": {
          "name": "domain",
          "type": "varchar",
          "primaryKey": false,
          "notNull": true
        },
        "markdown": {
          "name": "markdown",
          "type": "text",
          "primaryKey": false,
          "notNull": true
        },
        "scope": {
          "name": "scope",
          "type": "scope",
          "typeSchema": "public",
          "primaryKey": false,
          "notNull": true
        },
        "pos_x": {
          "name": "pos_x",
          "type": "integer",
          "primaryKey": false,
          "notNull": true
        },
        "pos_y": {
          "name": "pos_y",
          "type": "integer",
          "primaryKey": false,
          "notNull": true
        },
        "created_at": {
          "name": "created_at",
          "type": "timestamp",
          "primaryKey": false,
          "notNull": true,
          "default": "now()"
        },
        "updated_at": {
          "name": "updated_at",
          "type": "timestamp",
          "primaryKey": false,
          "notNull": true,
          "default": "now()"
        },
        "deleted_at": {
          "name": "deleted_at",
          "type": "timestamp",
          "primaryKey": false,
          "notNull": false
        }
      },
      "indexes": {
        "local_id_user_id_target_url_nodes_idx": {
          "name": "local_id_user_id_target_url_nodes_idx",
          "columns": [
            {
              "expression": "local_id",
              "isExpression": false,
              "asc": true,
              "nulls": "last"
            },
            {
              "expression": "user_id",
              "isExpression": false,
              "asc": true,
              "nulls": "last"
            },
            {
              "expression": "target_url",
              "isExpression": false,
              "asc": true,
              "nulls": "last"
            }
          ],
          "isUnique": true,
          "where": "\"node_table\".\"deleted_at\" is null",
          "concurrently": false,
          "method": "btree",
          "with": {}
        }
      },
      "foreignKeys": {
        "node_table_user_id_user_table_id_fk": {
          "name": "node_table_user_id_user_table_id_fk",
          "tableFrom": "node_table",
          "tableTo": "user_table",
          "columnsFrom": [
            "user_id"
          ],
          "columnsTo": [
            "id"
          ],
          "onDelete": "no action",
          "onUpdate": "no action"
        }
      },
      "compositePrimaryKeys": {},
      "uniqueConstraints": {},
      "policies": {},
      "checkConstraints": {},
      "isRLSEnabled": false
    },
    "public.user_table": {
      "name": "user_table",
      "schema": "",
      "columns": {
        "id": {
          "name": "id",
          "type": "serial",
          "primaryKey": true,
          "notNull": true
        },
        "google_id": {
          "name": "google_id",
          "type": "varchar",
          "primaryKey": false,
          "notNull": true
        },
        "name": {
          "name": "name",
          "type": "varchar",
          "primaryKey": false,
          "notNull": true
        },
        "email": {
          "name": "email",
          "type": "varchar",
          "primaryKey": false,
          "notNull": true
        },
        "roles": {
          "name": "roles",
          "type": "role[]",
          "primaryKey": false,
          "notNull": true
        },
        "profile_url": {
          "name": "profile_url",
          "type": "varchar",
          "primaryKey": false,
          "notNull": false
        },
        "created_at": {
          "name": "created_at",
          "type": "timestamp",
          "primaryKey": false,
          "notNull": true,
          "default": "now()"
        },
        "updated_at": {
          "name": "updated_at",
          "type": "timestamp",
          "primaryKey": false,
          "notNull": true,
          "default": "now()"
        },
        "deleted_at": {
          "name": "deleted_at",
          "type": "timestamp",
          "primaryKey": false,
          "notNull": false
        }
      },
      "indexes": {},
      "foreignKeys": {},
      "compositePrimaryKeys": {},
      "uniqueConstraints": {
        "user_table_google_id_unique": {
          "name": "user_table_google_id_unique",
          "nullsNotDistinct": false,
          "columns": [
            "google_id"
          ]
        }
      },
      "policies": {},
      "checkConstraints": {},
      "isRLSEnabled": false
    }
  },
  "enums": {
    "public.role": {
      "name": "role",
      "schema": "public",
      "values": [
        "general",
        "admin"
      ]
    },
    "public.scope": {
      "name": "scope",
      "schema": "public",
      "values": [
        "global",
        "domain",
        "full-path"
      ]
    }
  },
  "schemas": {},
  "sequences": {},
  "roles": {},
  "policies": {},
  "views": {},
  "_meta": {
    "columns": {},
    "schemas": {},
    "tables": {}
  }
}